Workbook

Sheet Dashboard
A1: TD BANK GROUP FINANCIAL ANALYSIS | J1: Made by: Carter Goveas | Y1: TD REVENUE: HISTORICAL VS FORECAST CHART | AD1: TD REPORTED VS ADJUSTED ROE CHART | AH1: TD CREDIT RISK: PCL/AVERAGE LOANS CHART
A2: Historical Analysis: 2021-2025 | Forecast: 2026-2028 | J2: Aug. 26, 2026 | Y2: Year | Z2: Actual Revenue (CAD billions) | AA2: Forecast Revenue (CAD billions) | AD2: Year | AE2: Reported ROE | AF2: Adjusted ROE | AH2: Year | AI2: PCL/Average Loans
Y3: 2021 | Z3: ='Raw Data'!B7/1000 -> 42.693 | AD3: 2021 | AE3: ='Raw Data'!B28 -> 0.155 | AF3: ='Raw Data'!B29 -> 0.159 | AH3: 2022 | AI3: =Ratios!B22 -> 0.0013735265
A4: 2025 Revenue (CAD billions) | B4: 2025 Net Income (CAD billions) | C4: 2025 Reported ROE | D4: 2025 CET1 Ratio | E4: 2025 PCL/Average Loans | Y4: 2022 | Z4: ='Raw Data'!C7/1000 -> 49.032 | AD4: 2022 | AE4: ='Raw Data'!C28 -> 0.18 | AF4: ='Raw Data'!C29 -> 0.159 | AH4: 2023 | AI4: =Ratios!C22 -> 0.0033966612
A5: ='Raw Data'!F7/1000 -> 67.777 | B5: ='Raw Data'!F11/1000 -> 20.538 | C5: ='Raw Data'!F28 -> 0.178 | D5: ='Raw Data'!F30 -> 0.147 | E5: =Ratios!E22 -> 0.0047367732 | Y5: 2023 | Z5: ='Raw Data'!D7/1000 -> 50.492 | AD5: 2023 | AE5: ='Raw Data'!D28 -> 0.101 | AF5: ='Raw Data'!D29 -> 0.144 | AH5: 2024 | AI5: =Ratios!D22 -> 0.004609059
Y6: 2024 | Z6: ='Raw Data'!E7/1000 -> 57.223 | AD6: 2024 | AE6: ='Raw Data'!E28 -> 0.082 | AF6: ='Raw Data'!E29 -> 0.136 | AH6: 2025 | AI6: =Ratios!E22 -> 0.0047367732
Y7: 2025 | Z7: ='Raw Data'!F7/1000 -> 67.777 | AA7: ='Raw Data'!F7/1000 -> 67.777 | AD7: 2025 | AE7: ='Raw Data'!F28 -> 0.178 | AF7: ='Raw Data'!F29 -> 0.129
Y8: 2026E | AA8: =Forecast!C20/1000 -> 71.16585
Y9: 2027E | AA9: =Forecast!D20/1000 -> 74.368313
Y10: 2028E | AA10: =Forecast!E20/1000 -> 77.343046
Y13: TD REVENUE GROWTH CHART
Y14: Year | Z14: Revenue (CAD billions)
Y15: 2021 | Z15: ='Raw Data'!B7/1000 -> 42.693
Y16: 2022 | Z16: ='Raw Data'!C7/1000 -> 49.032
Y17: 2023 | Z17: ='Raw Data'!D7/1000 -> 50.492
Y18: 2024 | Z18: ='Raw Data'!E7/1000 -> 57.223
Y19: 2025 | Z19: ='Raw Data'!F7/1000 -> 67.777
A38: KEY ANALYTICAL TAKEAWAYS
A39: 1. Revenue Growth
A40: - TD's reported revenue increased from $42.7B CAD in 2021 to $67.8B in 2025, representing a 12.3% CAGR.
A42: 2. Profitability
A43: - Reported ROE was volatile over the period, while adjusted ROE declined from 15.9% in 2021 to 12.9% in 2025, showing a more consistent downward trend in underlying profitability.
A45: 3. Credit Risk
A46: - PCL as a percentage of average loans increased from 0.14% in 2022 to 0.47% in 2025, although the increase moderated considerably between 2024 and 2025.
A48: 4. Forecast
A49: - Under the base-case assumptions, revenue is forecast to increase from $67.8B in 2025 to approximately $77.3B by 2028, reflecting progressively moderating annual revenue growth assumptions.
A51: 5. Valuation
A52: - TD's share price increased to $115.16M in 2025 from $89.64M in 2025, while its P/B ratio rose to 1.67 in 2025 from 1.29 in 2024, indicating a higher market valuation relative to book value. Its 2025 P/E ratio of 9.96 remained below its five-year average of 12.18.

Sheet Raw Data
A1: **Source: TD Bank Group Annual Reports 2021-2025 (See Sources & Notes). Historical figures reflect values reported in the respective fiscal-year reports and may differ from subsequently restated comparative figures
A2: *Financial figures in CAD millions, unless otherwise stated
A3: INCOME STATEMENT
A4: Metric | B4: 2021 | C4: 2022 | D4: 2023 | E4: 2024 | F4: 2025
A5: Net Interest Income | B5: 24131 | C5: 27353 | D5: 29944 | E5: 30472 | F5: 33062
A6: Non-Interest Income | B6: 18562 | C6: 21679 | D6: 20548 | E6: 26751 | F6: 34715
A7: Total Revenue | B7: 42693 | C7: 49032 | D7: 50492 | E7: 57223 | F7: 67777
A8: Provision for Credit Losses | B8: -224 | C8: 1067 | D8: 2933 | E8: 4253 | F8: 4506
A9: Non-Interest Expenses | B9: 23076 | C9: 24641 | D9: 30768 | E9: 35493 | F9: 33539
A10: Income Before Income Taxes | B10: 17134 | C10: 20424 | D10: 13086 | E10: 10830 | F10: 23643
A11: Net Income | B11: 14298 | C11: 17429 | D11: 10782 | E11: 8842 | F11: 20538
A12: Net Income Availible to Common Shareholders | B12: 14049 | C12: 17170 | D12: 10219 | E12: 8316 | F12: 19973
A13: Basic EPS | B13: 7.73 | C13: 9.48 | D13: 5.61 | E13: 4.73 | F13: 11.57
A14: Diluted EPS | B14: 7.72 | C14: 9.47 | D14: 5.6 | E14: 4.72 | F14: 11.56
A15: Dividends Per Common Share | B15: 3.16 | C15: 3.56 | D15: 3.84 | E15: 4.08 | F15: 4.2
A17: BALANCE SHEET
A18: Metric | B18: 2021 | C18: 2022 | D18: 2023 | E18: 2024 | F18: 2025
A19: Total Assets | B19: 1728672 | C19: 1917528 | D19: 1957024 | E19: 2061751 | F19: 2094558
A20: Loans, Net of Allowance | B20: 722622 | C20: 831043 | D20: 895947 | E20: 949549 | F20: 953012
A21: Total Deposits | B21: 1125125 | C21: 1229970 | D21: 1198190 | E21: 1268680 | F21: 1267104
A22: Total Liabilities | B22: 1628854 | C22: 1806145 | D22: 1844917 | E22: 1946591 | F22: 1966731
A23: Total Equity | B23: 99818 | C23: 111383 | D23: 112107 | E23: 115160 | F23: 127827
A24: Common Shares Outstanding | B24: 1817.7 | C24: 1810.5 | D24: 1822.5 | E24: 1750.1 | F24: 1689.5
A26: BANKING KPIs
A27: Metric | B27: 2021 | C27: 2022 | D27: 2023 | E27: 2024 | F27: 2025
A28: Reported ROE | B28: 0.155 | C28: 0.18 | D28: 0.101 | E28: 0.082 | F28: 0.178
A29: Adjusted ROE | B29: 0.159 | C29: 0.159 | D29: 0.144 | E29: 0.136 | F29: 0.129
A30: CET1 Ratio | B30: 0.152 | C30: 0.162 | D30: 0.144 | E30: 0.131 | F30: 0.147
A31: Efficiency Ratio | B31: 0.541 | C31: 0.503 | D31: 0.609 | E31: 0.62 | F31: 0.495
A32: Adjusted Efficiency Ratio | B32: 0.537 | C32: 0.528 | D32: 0.529 | E32: 0.581 | F32: 0.584
A33: Book Value Per Share | B33: 51.66 | C33: 55 | D33: 56.58 | E33: 59.59 | F33: 68.78
A34: Closing Share Price (TSX) | B34: 89.64 | C34: 87.19 | D34: 77.46 | E34: 76.97 | F34: 115.16

Sheet Ratios
A1: *Financial figures in CAD millions, unless otherwise stated
A2: GROWTH ANALYSIS
A3: Metric | B3: 2022 | C3: 2023 | D3: 2024 | E3: 2025 | F3: 2021-2025 CAGR
A4: Revenue Growth | B4: ='Raw Data'!C7/'Raw Data'!B7-1 -> 0.14847867 | C4: ='Raw Data'!D7/'Raw Data'!C7-1 -> 0.029776473 | D4: ='Raw Data'!E7/'Raw Data'!D7-1 -> 0.13330825 | E4: ='Raw Data'!F7/'Raw Data'!E7-1 -> 0.18443633 | F4: =('Raw Data'!F7/'Raw Data'!B7)^(1/4)-1 -> 0.12248725
A5: Net Income Growth | B5: ='Raw Data'!C11/'Raw Data'!B11-1 -> 0.21898168 | C5: ='Raw Data'!D11/'Raw Data'!C11-1 -> -0.38137587 | D5: ='Raw Data'!E11/'Raw Data'!D11-1 -> -0.17992951 | E5: ='Raw Data'!F11/'Raw Data'!E11-1 -> 1.3227777 | F5: =('Raw Data'!F11/'Raw Data'!B11)^(1/4)-1 -> 0.09476452
A6: Diluted EPS Growth | B6: ='Raw Data'!C14/'Raw Data'!B14-1 -> 0.22668394 | C6: ='Raw Data'!D14/'Raw Data'!C14-1 -> -0.40865892 | D6: ='Raw Data'!E14/'Raw Data'!D14-1 -> -0.15714286 | E6: ='Raw Data'!F14/'Raw Data'!E14-1 -> 1.4491525 | F6: =('Raw Data'!F14/'Raw Data'!B14)^(1/4)-1 -> 0.10620377
A7: Loan Growth | B7: ='Raw Data'!C20/'Raw Data'!B20-1 -> 0.15003833 | C7: ='Raw Data'!D20/'Raw Data'!C20-1 -> 0.078099449 | D7: ='Raw Data'!E20/'Raw Data'!D20-1 -> 0.0598272 | E7: ='Raw Data'!F20/'Raw Data'!E20-1 -> 0.0036469945 | F7: =('Raw Data'!F20/'Raw Data'!B20)^(1/4)-1 -> 0.071634773
A8: Deposit Growth | B8: ='Raw Data'!C21/'Raw Data'!B21-1 -> 0.093185202 | C8: ='Raw Data'!D21/'Raw Data'!C21-1 -> -0.025838029 | D8: ='Raw Data'!E21/'Raw Data'!D21-1 -> 0.058830403 | E8: ='Raw Data'!F21/'Raw Data'!E21-1 -> -0.001242236 | F8: =('Raw Data'!F21/'Raw Data'!B21)^(1/4)-1 -> 0.030155705
A9: Asset Growth | B9: ='Raw Data'!C19/'Raw Data'!B19-1 -> 0.10924918 | C9: ='Raw Data'!D19/'Raw Data'!C19-1 -> 0.020597352 | D9: ='Raw Data'!E19/'Raw Data'!D19-1 -> 0.053513396 | E9: ='Raw Data'!F19/'Raw Data'!E19-1 -> 0.015912203 | F9: =('Raw Data'!F19/'Raw Data'!B19)^(1/4)-1 -> 0.049167788
A10: Dividend Growth | B10: ='Raw Data'!C15/'Raw Data'!B15-1 -> 0.12658228 | C10: ='Raw Data'!D15/'Raw Data'!C15-1 -> 0.078651685 | D10: ='Raw Data'!E15/'Raw Data'!D15-1 -> 0.0625 | E10: ='Raw Data'!F15/'Raw Data'!E15-1 -> 0.029411765 | F10: =('Raw Data'!F15/'Raw Data'!B15)^(1/4)-1 -> 0.073718787
A12: PROFITABILITY ANALYSIS
A13: Metric | B13: 2022 | C13: 2023 | D13: 2024 | E13: 2025
A14: Return on Assets (ROA) | B14: ='Raw Data'!C11/(('Raw Data'!B19+'Raw Data'!C19)/2) -> 0.00956009 | C14: ='Raw Data'!D11/(('Raw Data'!C19+'Raw Data'!D19)/2) -> 0.0055655467 | D14: ='Raw Data'!E11/(('Raw Data'!D19+'Raw Data'!E19)/2) -> 0.0044003459 | E14: ='Raw Data'!F11/(('Raw Data'!E19+'Raw Data'!F19)/2) -> 0.0098828071
A15: Reported ROE | B15: ='Raw Data'!C28 -> 0.18 | C15: ='Raw Data'!D28 -> 0.101 | D15: ='Raw Data'!E28 -> 0.082 | E15: ='Raw Data'!F28 -> 0.178
A16: Adjusted ROE | B16: ='Raw Data'!C29 -> 0.159 | C16: ='Raw Data'!D29 -> 0.144 | D16: ='Raw Data'!E29 -> 0.136 | E16: ='Raw Data'!F29 -> 0.129
A18: OPERATING & CREDIT ANALYSIS
A19: Metric | B19: 2022 | C19: 2023 | D19: 2024 | E19: 2025
A20: Reported Efficiency Ratio | B20: ='Raw Data'!C31 -> 0.503 | C20: ='Raw Data'!D31 -> 0.609 | D20: ='Raw Data'!E31 -> 0.62 | E20: ='Raw Data'!F31 -> 0.495
A21: Adjusted Efficiency Ratio | B21: ='Raw Data'!C32 -> 0.528 | C21: ='Raw Data'!D32 -> 0.529 | D21: ='Raw Data'!E32 -> 0.581 | E21: ='Raw Data'!F32 -> 0.584
A22: PCL/Average Loans | B22: ='Raw Data'!C8/(('Raw Data'!B20+'Raw Data'!C20)/2) -> 0.0013735265 | C22: ='Raw Data'!D8/(('Raw Data'!C20+'Raw Data'!D20)/2) -> 0.0033966612 | D22: ='Raw Data'!E8/(('Raw Data'!D20+'Raw Data'!E20)/2) -> 0.004609059 | E22: ='Raw Data'!F8/(('Raw Data'!E20+'Raw Data'!F20)/2) -> 0.0047367732
A24: CAPITAL & VALUATION ANALYSIS
A25: Metric | B25: 2021 | C25: 2022 | D25: 2023 | E25: 2024 | F25: 2025 | G25: 5-Year Average
A26: CET1 Ratio | B26: ='Raw Data'!B30 -> 0.152 | C26: ='Raw Data'!C30 -> 0.162 | D26: ='Raw Data'!D30 -> 0.144 | E26: ='Raw Data'!E30 -> 0.131 | F26: ='Raw Data'!F30 -> 0.147 | G26: =AVERAGE(B26:F26) -> 0.1472
A27: Book Value Per Share | B27: ='Raw Data'!B33 -> 51.66 | C27: ='Raw Data'!C33 -> 55 | D27: ='Raw Data'!D33 -> 56.58 | E27: ='Raw Data'!E33 -> 59.59 | F27: ='Raw Data'!F33 -> 68.78 | G27: =AVERAGE(B27:F27) -> 58.322
A28: Closing Share Price | B28: ='Raw Data'!B34 -> 89.64 | C28: ='Raw Data'!C34 -> 87.19 | D28: ='Raw Data'!D34 -> 77.46 | E28: ='Raw Data'!E34 -> 76.97 | F28: ='Raw Data'!F34 -> 115.16 | G28: =AVERAGE(B28:F28) -> 89.284
A29: Price-to-Book Ratio | B29: =B28/B27 -> 1.7351916 | C29: =C28/C27 -> 1.5852727 | D29: =D28/D27 -> 1.369035 | E29: =E28/E27 -> 1.2916597 | F29: =F28/F27 -> 1.6743239 | G29: =AVERAGE(B29:F29) -> 1.5310966
A30: P/E Ratio | B30: ='Raw Data'!B34/'Raw Data'!B14 -> 11.611399 | C30: ='Raw Data'!C34/'Raw Data'!C14 -> 9.2069694 | D30: ='Raw Data'!D34/'Raw Data'!D14 -> 13.832143 | E30: ='Raw Data'!E34/'Raw Data'!E14 -> 16.307203 | F30: ='Raw Data'!F34/'Raw Data'!F14 -> 9.9619377 | G30: =AVERAGE(B30:F30) -> 12.18393

Sheet Forecast
A1: *Financial figures in CAD millions, unless otherwise stated
A2: BASE-CASE FORECAST ASSUMPTIONS
A3: Forecast period: 2026E-2028E | Based on analyst assumptions
A4: Metric | B4: 2026E | C4: 2027E | D4: 2028E
A5: Revenue Growth | B5: =B15 -> 0.05 | C5: 0.045 | D5: 0.04
A6: PCL/Average Loans | B6: 0.0045 | C6: 0.004 | D6: 0.0038
A7: Expense Growth | B7: 0.03 | C7: 0.03 | D7: 0.03
A8: Tax Rate | B8: 0.21 | C8: 0.21 | D8: 0.21
A9: Loan Growth | B9: 0.03 | C9: 0.035 | D9: 0.04
A10: Deposit Growth | B10: 0.025 | C10: 0.03 | D10: 0.03
A12: HYPOTHETICAL SCENARIOS
A13: Scenario | B13: Revenue Growth | C13: 2025 Revenue | D13: 2026 Revenue | E13: 2027 Revenue | F13: 2028 Revenue
A14: Bear | B14: 0.03 | C14: 67777 | D14: =Forecast!C14*(1+Forecast!B14) -> 69810.31 | E14: =D14*(1+B14) -> 71904.619 | F14: =E14*(1+B14) -> 74061.758
A15: Base | B15: 0.05 | C15: 67777 | D15: =C15*(1+B15) -> 71165.85 | E15: =D15*(1+B15) -> 74724.143 | F15: =E15*(1+B15) -> 78460.35
A16: Bull | B16: 0.07 | C16: 67777 | D16: =C16*(1+B16) -> 72521.39 | E16: =D16*(1+B16) -> 77597.887 | F16: =E16*(1+B16) -> 83029.739
A18: FINANCIAL FORECAST
A19: Metric | B19: 2025A | C19: 2026E | D19: 2027E | E19: 2028E
A20: Total Revenue | B20: ='Raw Data'!F7 -> 67777 | C20: =B20*(1+B5) -> 71165.85 | D20: =C20*(1+C5) -> 74368.313 | E20: =D20*(1+D5) -> 77343.046
A21: Loans | B21: ='Raw Data'!F20 -> 953012 | C21: =B21*(1+B9) -> 981602.36 | D21: =C21*(1+C9) -> 1015958.4 | E21: =D21*(1+D9) -> 1056596.8
A22: Deposits | B22: ='Raw Data'!F21 -> 1267104 | C22: =B22*(1+B10) -> 1298781.6 | D22: =C22*(1+C10) -> 1337745 | E22: =D22*(1+D10) -> 1377877.4
A23: Average Loans | C23: =(B21+C21)/2 -> 967307.18 | D23: =(C21+D21)/2 -> 998780.4 | E23: =(D21+E21)/2 -> 1036277.6
A24: Provision for Credit Losses | B24: ='Raw Data'!F8 -> 4506 | C24: =C23*B6 -> 4352.8823 | D24: =D23*C6 -> 3995.1216 | E24: =E23*D6 -> 3937.8549
A25: Non-Interest Expenses | B25: ='Raw Data'!F9 -> 33539 | C25: =B25*(1+B7) -> 34545.17 | D25: =C25*(1+C7) -> 35581.525 | E25: =D25*(1+D7) -> 36648.971
A26: Pre-Tax Income | C26: =C20-C24-C25 -> 32267.798 | D26: =D20-D24-D25 -> 34791.667 | E26: =E20-E24-E25 -> 36756.22
A27: Income Taxes | C27: =C26*B8 -> 6776.2375 | D27: =D26*C8 -> 7306.25 | E27: =E26*D8 -> 7718.8062
A28: Net Income | B28: ='Raw Data'!F11 -> 20538 | C28: =C26-C27 -> 25491.56 | D28: =D26-D27 -> 27485.417 | E28: =E26-E27 -> 29037.414
A30: FORECAST METHODOLOGY
A31: Total Revenue: Projected using annual growth assumptions of 5% in 2026, 4.5% in 2027, and 4% in 2027.
A32: Loans: Projected using annual growth assumptions of 3% in 2026, 3.5% in 2027, and 4% in 2028.
A33: Deposits: Projected using annual growth assumptions of 2.5% in 2026, 3% in 2027, and 3% in 2028.
A34: Average Loans: Projected by calculating the average loans of the current and previous year.
A35: Provision for Credit Losses: Projected using annual growth assumptions (PCL/Average Loans) of 0.45% in 2026, 0.4% in 2027, and 0.38% in 2028.
A36: Non-Interest Expenses: Projected using annual growth assumption of 3% from 2026 through 2028.
A37: Pre-Tax Income: Projected by subctracting Total Revenue by Provision for Credit Losses by Non-Interest Expenses.
A38: Income Taxes: Projected using annual growth assumption of 21% from 2026 through 2028.
A39: Net Income: Projected by subtracting Pre-Tax Income by Income Taxes.

Sheet Sources & Notes
A1: *Historical financial data was obtained from publicly availible TD Bank Group annual reports. Calculated ratios and forecasts represent the author's calculations and illustrative assumptions.
A2: Source | B2: Data Used | C2: Link to Source
A3: TD Bank Group Annual Report 2025 | B3: Income Statement, Balance Sheet, Banking KPIs in 'Raw Data' sheet | C3: https://www.td.com/content/dam/tdcom/canada/about-td/pdf/quarterly-results/2025/q4/2025-annual-report-en.pdf
A4: TD Bank Group Annual Report 2024 | B4: Income Statement, Balance Sheet, Banking KPIs in 'Raw Data' sheet | C4: https://www.td.com/content/dam/tdcom/canada/about-td/pdf/quarterly-results/2024/q4/2024-annual-report-en.pdf
A5: TD Bank Group Annual Report 2023 | B5: Income Statement, Balance Sheet, Banking KPIs in 'Raw Data' sheet | C5: https://www.td.com/content/dam/tdcom/canada/about-td/pdf/quarterly-results/2023/2023-annual-report-e.pdf
A6: TD Bank Group Annual Report 2022 | B6: Income Statement, Balance Sheet, Banking KPIs in 'Raw Data' sheet | C6: https://www.td.com/content/dam/tdcom/canada/about-td/for-investors/investor-relations/ar2022-Complete-Report.pdf
A7: TD Bank Group Annual Report 2021 | B7: Income Statement, Balance Sheet, Banking KPIs in 'Raw Data' sheet | C7: https://www.td.com/content/dam/tdcom/canada/about-td/pdf/annual-meetings/2022/ar2021-Complete-Report.pdf
A9: Methodology Note: This was my first time using excel and building a financial analysis. For full transparency, ChatGPT was used as an assistive tool in the development of this project.
